MANIFEST.in
setup.py
testdef/__init__.py
testdef/tests.py
testdef.egg-info/PKG-INFO
testdef.egg-info/SOURCES.txt
testdef.egg-info/dependency_links.txt
testdef.egg-info/top_level.txt
testdef.egg-info/zip-safe