Metadata-Version: 1.1
Name: testdef
Version: 0.1
Summary: Testdef is an emerging test definition interchange intended for storing and describing tests in a public repository.
Home-page: https://github.com/zyga/testdef
Author: Zygmunt Krynicki
Author-email: zygmunt.krynicki@canonical.com
License: UNKNOWN
Platform: UNKNOWN
Classifier: Development Status :: 1 - Planning
Classifier: Intended Audience :: Developers
Classifier: License :: OSI Approved :: GNU Library or Lesser General Public License (LGPL)
Classifier: Operating System :: OS Independent
Classifier: Programming Language :: Python
Classifier: Programming Language :: Python :: 2.7
Classifier: Programming Language :: Python :: 3.2
Classifier: Topic :: Software Development :: Testing
